yplib/__init__.py
yplib/chart.py
yplib/chart_html.py
yplib/common_package.py
yplib/db.py
yplib/file.py
yplib/http_util.py
yplib/index.py
yplib/mail.py
yplib/mail_html.py
yplib/markdown.py
yplib/multi_thread.py
yplib/temp.py
yplib-8.9.1.dist-info/licenses/LICENSE
yplib-8.9.1.dist-info/METADATA
yplib-8.9.1.dist-info/WHEEL
yplib-8.9.1.dist-info/top_level.txt
yplib-8.9.1.dist-info/RECORD
