Metadata-Version: 2.4
Name: yplib
Version: 8.9.1
Summary: util
Author: yangpu
Author-email: wantwaterfish@gmail.com
License: MIT
Classifier: Programming Language :: Python :: 3
Classifier: Operating System :: OS Independent
Requires-Python: >=3.10
License-File: LICENSE
Requires-Dist: openpyxl>=3.1.2
Requires-Dist: xlrd>=2.0.1
Requires-Dist: bs4>=0.0.2
Requires-Dist: requests>=2.32.3
Requires-Dist: PyMySQL>=1.1.0
Requires-Dist: pyarrow>=16.0.0
Requires-Dist: sqlparse>=0.5.0
Requires-Dist: pandas>=2.2.2
Dynamic: author
Dynamic: author-email
Dynamic: classifier
Dynamic: description
Dynamic: description-content-type
Dynamic: license
Dynamic: license-file
Dynamic: requires-dist
Dynamic: requires-python
Dynamic: summary
